jxa/Progress.py
jxa/genmixin.py
jxa-0.0.1.dist-info/LICENSE
jxa-0.0.1.dist-info/METADATA
jxa-0.0.1.dist-info/WHEEL
jxa-0.0.1.dist-info/top_level.txt
jxa-0.0.1.dist-info/RECORD
