Metadata-Version: 2.1
Name: jxa
Version: 0.0.1
Summary: Generic Libraries
Home-page: https://github.com/jkedra/jxa
Author: Jurek Kedra
Author-email: jurek.kedra@gmail.com
License: UNKNOWN
Platform: UNKNOWN
Classifier: Programming Language :: Python :: 3
Classifier: License :: OSI Approved :: MIT License
Classifier: Operating System :: OS Independent
